odoo/addons/product_cost_security/README.rst
odoo/addons/product_cost_security/__init__.py
odoo/addons/product_cost_security/__manifest__.py
odoo/addons/product_cost_security/i18n/es.po
odoo/addons/product_cost_security/i18n/product_cost_security.pot
odoo/addons/product_cost_security/models/__init__.py
odoo/addons/product_cost_security/models/product.py
odoo/addons/product_cost_security/readme/CONFIGURE.rst
odoo/addons/product_cost_security/readme/CONTRIBUTORS.rst
odoo/addons/product_cost_security/readme/DESCRIPTION.rst
odoo/addons/product_cost_security/readme/USAGE.rst
odoo/addons/product_cost_security/security/product_cost_security.xml
odoo/addons/product_cost_security/static/description/icon.png
odoo/addons/product_cost_security/static/description/index.html
odoo/addons/product_cost_security/views/product_views.xml
odoo11_addon_product_cost_security-11.0.1.0.0.99.dev5.dist-info/METADATA
odoo11_addon_product_cost_security-11.0.1.0.0.99.dev5.dist-info/WHEEL
odoo11_addon_product_cost_security-11.0.1.0.0.99.dev5.dist-info/top_level.txt
odoo11_addon_product_cost_security-11.0.1.0.0.99.dev5.dist-info/RECORD
